{
  "questions": [
    {
      "topic": "Out-of-order, Pipeline, Microarchitecture",
      "text": "Процесори, що використовують out of order execution, користуються такими поняттями як Issue та Retire. Поясніть, що вони означають і де використовуються"
    },
    {
      "topic": "Out-of-order, Pipeline, Microarchitecture",
      "text": "Що таке Pipeline?"
    },
    {
      "topic": "Out-of-order, Pipeline, Microarchitecture",
      "text": "Що таке Pipeline hazards?"
    },
    {
      "topic": "Out-of-order, Pipeline, Microarchitecture",
      "text": "Що таке Speculative execution?"
    },
    {
      "topic": "Out-of-order, Pipeline, Microarchitecture",
      "text": "Що таке алгоритм Томасуло?"
    },
    {
      "topic": "Out-of-order, Pipeline, Microarchitecture",
      "text": "Що таке мікрокод?"
    },
    {
      "topic": "Out-of-order, Pipeline, Microarchitecture",
      "text": "Що таке суперскалярність?"
    },
    {
      "topic": "Out-of-order, Pipeline, Microarchitecture",
      "text": "Що таке форвардинг конвеєром?"
    },
    {
      "topic": "Out-of-order, Pipeline, Microarchitecture",
      "text": "Що таке перейменування регістрів?"
    },
    {
      "topic": "Out-of-order, Pipeline, Microarchitecture",
      "text": "Що таке load delay slot? Branch delay slot?"
    },
    {
      "topic": "Out-of-order, Pipeline, Microarchitecture",
      "text": "Що таке Re-order buffer?"
    },
    {
      "topic": "Out-of-order, Pipeline, Microarchitecture",
      "text": "Що таке блоки резервування (reservation stations)?"
    },
    {
      "topic": "Out-of-order, Pipeline, Microarchitecture",
      "text": "Що таке конфлікти даних конвеєра? (data hazards)"
    },
    {
      "topic": "Out-of-order, Pipeline, Microarchitecture",
      "text": "Що таке конфлікти керування конвеєра (control hazards or branching hazards)?"
    },
    {
      "topic": "Out-of-order, Pipeline, Microarchitecture",
      "text": "Що таке структурні конфлікти конвеєра?"
    },
    {
      "topic": "Out-of-order, Pipeline, Microarchitecture",
      "text": "Для чого потрібно out-of-order execution - переворядкування команд?"
    },
    {
      "topic": "Out-of-order, Pipeline, Microarchitecture",
      "text": "Перерахуйте залежності між даними, які можуть траплятися під час виконання програми"
    },
    {
      "topic": "Пам'ять: DRAM, SRAM, архітектура",
      "text": "Які характерні особливості DRAM?"
    },
    {
      "topic": "Пам'ять: DRAM, SRAM, архітектура",
      "text": "Що таке SRAM?"
    },
    {
      "topic": "Пам'ять: DRAM, SRAM, архітектура",
      "text": "Що таке DRAM?"
    },
    {
      "topic": "Пам'ять: DRAM, SRAM, архітектура",
      "text": "В чому різниця між ROM, EPROM та EEPROM?"
    },
    {
      "topic": "Пам'ять: DRAM, SRAM, архітектура",
      "text": "Чим DDR SDRAM відрізняється від DDR2 SDRAM?"
    },
    {
      "topic": "Пам'ять: DRAM, SRAM, архітектура",
      "text": "Як із логічної (лінійної) адреси отримується фізична адреса?"
    },
    {
      "topic": "Пам'ять: DRAM, SRAM, архітектура",
      "text": "Що таке багатопортова пам'ять?"
    },
    {
      "topic": "Пам'ять: DRAM, SRAM, архітектура",
      "text": "Яĸ працює SDRAM?"
    },
    {
      "topic": "Пам'ять: DRAM, SRAM, архітектура",
      "text": "Яĸ працює Для чого служать сигнали RAS та CAS? Яĸ фунĸціонує DDR SDRAM?"
    },
    {
      "topic": "Пам'ять: DRAM, SRAM, архітектура",
      "text": "Яĸ працює Для чого служать сигнали RAS та CAS? Яĸ фунĸціонує DDR SDRAM?"
    },
    {
      "topic": "Пам'ять: DRAM, SRAM, архітектура",
      "text": "Опишіть принципи їх фунĸціювання та можливу ĸонструĸцію ĸомірĸи пам’яті DRAM та SRAM."
    },
    {
      "topic": "Пам'ять: DRAM, SRAM, архітектура",
      "text": "В чому суть cold boot attack?"
    },
    {
      "topic": "Пам'ять: DRAM, SRAM, архітектура",
      "text": "В чому суть row hammer attack?"
    },
    {
      "topic": "Пам'ять: DRAM, SRAM, архітектура",
      "text": "Що таĸе prefetch buffer DDR SDRAM (не плутати із prefetcher процесора!)"
    },
    {
      "topic": "Пам'ять: DRAM, SRAM, архітектура",
      "text": "Що таĸе DIMM, SIMM, NVRAM, GDDR? Яĸі хараĸтерні часи (memory timing) DRAM ви можете назвати?"
    },
    {
      "topic": "Пам'ять: DRAM, SRAM, архітектура",
      "text": "Навіщо потрібна ECC-пам’ять? Що таĸе Registered memory? Що таĸе FB-DIMM?"
    },
    {
      "topic": "ISA, SIMD, архітектури машин",
      "text": "Що таке CISC, RISC, VLIW? Наведіть приклади."
    },
    {
      "topic": "ISA, SIMD, архітектури машин",
      "text": "Що таке акумуляторні машини? Наведіть приклади."
    },
    {
      "topic": "ISA, SIMD, архітектури машин",
      "text": "Що таке реєстрові (register-register, load-store) машини? Наведіть приклади."
    },
    {
      "topic": "ISA, SIMD, архітектури машин",
      "text": "Що таке register-memory машини? Наведіть приклади."
    },
    {
      "topic": "ISA, SIMD, архітектури машин",
      "text": "Що таке стекові машини? Наведіть приклади."
    },
    {
      "topic": "ISA, SIMD, архітектури машин",
      "text": "Що таке CISC архітектура? Наведіть приклади і опишіть основні особливості."
    },
    {
      "topic": "ISA, SIMD, архітектури машин",
      "text": "Що таке RISC архітектура? Наведіть приклади і опишіть основні особливості."
    },
    {
      "topic": "ISA, SIMD, архітектури машин",
      "text": "Що таке VLIW архітектура? Наведіть приклади і опишіть основні особливості."
    },
    {
      "topic": "ISA, SIMD, архітектури машин",
      "text": "Що таке SIMD і які обчислення ним можна прискорити?"
    },
    {
      "topic": "ISA, SIMD, архітектури машин",
      "text": "Як за допомогою SIMD підрахувати довжину N-мірного вектора?"
    },
    {
      "topic": "ISA, SIMD, архітектури машин",
      "text": "Запропонуйте систему команд акумуляторної машини."
    },
    {
      "topic": "ISA, SIMD, архітектури машин",
      "text": "Що таке стекові машини? Наведіть приклади."
    },
    {
      "topic": "ISA, SIMD, архітектури машин",
      "text": "Нехай до ISA додано нові floating-point команди, що прискорюють обчислення вдвічі. Наскільки прискориться виконання програми, 20% часу якої витрачається на ці обчислення?"
    },
    {
      "topic": "ISA, SIMD, архітектури машин",
      "text": "Є два процесори: один із CPI 1.5 і частотою 2 ГГц, другий із CPI 1 і частотою 1.5 ГГц. Який ефективніший?"
    },
    {
      "topic": "ISA, SIMD, архітектури машин",
      "text": "Нехай SIMD дозволяє виконувати 2 floating-point операції за інструкцію, але має CPI = 2, тоді як скалярні мають CPI = 1.5. Чи буде виграш, якщо floating-point займають 30% часу виконання?"
    },
    {
      "topic": "ISA, SIMD, архітектури машин",
      "text": "Нехай SIMD дозволяє виконувати 4 floating-point операції за інструкцію, але має CPI = 2, тоді як скалярні мають CPI = 1.25. Чи буде виграш, якщо floating-point займають 30% часу виконання?"
    },
    {
      "topic": "ISA, SIMD, архітектури машин",
      "text": "Як за допомогою SIMD додати два вектори float?"
    },

    {
      "topic": "Паралельні обчислення, архітектури систем",
      "text": "Що таке concurrent computing та parallel computing?"
    },
    {
      "topic": "Паралельні обчислення, архітектури систем",
      "text": "Які є види паралелізму за Flynn’s taxonomy?"
    },
    {
      "topic": "Паралельні обчислення, архітектури систем",
      "text": "Які є рівні паралелізму в апаратурі (біти, інструкції, задачі)?"
    },
    {
      "topic": "Паралельні обчислення, архітектури систем",
      "text": "Які є види паралелізму задач: дрібнозернистий, крупнозернистий, приголомшливий?"
    },
    {
      "topic": "Паралельні обчислення, архітектури систем",
      "text": "Що таке PRAM (Parallel Random Access Machine)? Для чого використовується?"
    },
    {
      "topic": "Паралельні обчислення, архітектури систем",
      "text": "Що таке SMP (Symmetric Multiprocessing)?"
    },
    {
      "topic": "Паралельні обчислення, архітектури систем",
      "text": "Що таке SMT (Simultaneous Multithreading)?"
    },
    {
      "topic": "Паралельні обчислення, архітектури систем",
      "text": "У чому різниця між мультипроцесором і мультикомп’ютером?"
    },
    {
      "topic": "Паралельні обчислення, архітектури систем",
      "text": "У чому різниця між shared memory та distributed memory?"
    },
    {
      "topic": "Паралельні обчислення, архітектури систем",
      "text": "Що таке UMA та NUMA?"
    },
    {
      "topic": "Паралельні обчислення, архітектури систем",
      "text": "Що таке числові характеристики прискорення виконання задачі?"
    },
    {
      "topic": "Паралельні обчислення, архітектури систем",
      "text": "Що таке паралельне сповільнення?"
    },
    {
      "topic": "Паралельні обчислення, архітектури систем",
      "text": "Що таке надлінійне прискорення? За яких умов воно виникає?"
    },
    {
      "topic": "Паралельні обчислення, архітектури систем",
      "text": "У чому суть закону Амдала? Які його наслідки?"
    },
    {
      "topic": "Паралельні обчислення, архітектури систем",
      "text": "Що таке закон Густафсона?"
    },
    {
      "topic": "Паралельні обчислення, архітектури систем",
      "text": "Що таке залежності між задачами?"
    },
    {
      "topic": "Паралельні обчислення, архітектури систем",
      "text": "Сформулюйте умови незалежності задач за Бернштейном."
    },
    {
      "topic": "Паралельні обчислення, архітектури систем",
      "text": "Перелічіть види паралельних обчислювальних систем у порядку спадання їх інтегрованості (coupling). Обґрунтуйте."
    },
    {
      "topic": "Паралельні обчислення, архітектури систем",
      "text": "У чому суть паралельних систем із shared memory?"
    },
    {
      "topic": "Паралельні обчислення, архітектури систем",
      "text": "У чому суть паралельних систем із distributed memory?"
    },
    {
      "topic": "Паралельні обчислення, архітектури систем",
      "text": "Чим shared memory системи відрізняються від distributed memory систем?"
    },
    {
      "topic": "Паралельні обчислення, архітектури систем",
      "text": "Що означають абревіатури UMA та NUMA?"
    },
    {
      "topic": "Паралельні обчислення, архітектури систем",
      "text": "Чому виникла потреба в технології NUMA?"
    },
    {
      "topic": "Паралельні обчислення, архітектури систем",
      "text": "Що таке cache coherent NUMA (ccNUMA)?"
    },
    {
      "topic": "Паралельні обчислення, архітектури систем",
      "text": "Як забезпечується когерентність кешу у ccNUMA?"
    },
    {
      "topic": "Паралельні обчислення, архітектури систем",
      "text": "Як знайти середню латентність задач?"
    },
    {
      "topic": "Паралельні обчислення, архітектури систем",
      "text": "Як знайти середню пропускну здатність задач?"
    },
    {
      "topic": "Паралельні обчислення, архітектури систем",
      "text": "Як знайти середнє прискорення виконання задач?"
    },

    {
      "topic": "Паралельне програмування",
      "text": "Що таке стан гонитви (race condition)? Що таке гонитва даних (data race)? Яка достатня умова виникнення гонитви даних у C/C++?"
    },
    {
      "topic": "Паралельне програмування",
      "text": "Для чого використовується синхронізація при паралельному програмуванні? Які способи уникнення гонитви даних ви знаєте?"
    },
    {
      "topic": "Паралельне програмування",
      "text": "Що таке замок (Lock) і як з його допомогою досягається взаємне виключення?"
    },
    {
      "topic": "Паралельне програмування",
      "text": "Що таке критична секція?"
    },
    {
      "topic": "Паралельне програмування",
      "text": "Що таке взаємоблокування (deadlock)?"
    },
    {
      "topic": "Паралельне програмування",
      "text": "Що таке бар’єри синхронізації?"
    },
    {
      "topic": "Паралельне програмування",
      "text": "Що означає, що операція є атомарною? Чи є атомарною операція присвоєння змінної в C/C++, Python, Java, C#?"
    },
    {
      "topic": "Паралельне програмування",
      "text": "Що таке мютекс? Що таке рекурсивні мютекси і коли вони можуть бути корисними?"
    },
    {
      "topic": "Паралельне програмування",
      "text": "Що таке умовні змінні? Як їх використовують у задачі типу споживач-постачальник (consumer-producer)?"
    },
    {
      "topic": "Паралельне програмування",
      "text": "Що таке spurious wakeup? Як цьому протистояти? Хто буде пробуджений після notify()?"
    },
    {
      "topic": "Паралельне програмування",
      "text": "Які API для роботи з потоками ви знаєте? Що таке std::thread? Як запустити функцію в окремому потоці в C++?"
    },
    {
      "topic": "Паралельне програмування",
      "text": "Як передати аргументи у потік і отримати результат? Опишіть якомога більше способів."
    },
    {
      "topic": "Паралельне програмування",
      "text": "Що таке pthread?"
    },
    {
      "topic": "Паралельне програмування",
      "text": "Які засоби синхронізації з C++11 і новіших стандартів ви знаєте? Як атомарно виконати x += 1 у C++?"
    },
    {
      "topic": "Паралельне програмування",
      "text": "Що таке std::timed_mutex, std::recursive_timed_mutex, std::shared_timed_mutex? А std::lock_guard, std::unique_lock, std::shared_lock?"
    },
    {
      "topic": "Паралельне програмування",
      "text": "Для чого використовуються std::lock і std::try_lock у C++? Яку проблему вони вирішують?"
    },
    {
      "topic": "Паралельне програмування",
      "text": "Що таке RAII? Які переваги цього підходу порівняно з garbage collector?"
    },
    {
      "topic": "Паралельне програмування",
      "text": "Що таке thread-local data? Чим вони відрізняються від глобальних і локальних даних?"
    },
    {
      "topic": "Паралельне програмування",
      "text": "Що таке бар’єр (barrier) як засіб синхронізації потоків?"
    },
    {
      "topic": "Паралельне програмування",
      "text": "Що таке семафори? Як ними користуватися? Опишіть вирішення задачі постачальник-споживач із семафорами."
    },
    {
      "topic": "Паралельне програмування",
      "text": "Що таке монітор як засіб паралельного програмування?"
    },
    {
      "topic": "Паралельне програмування",
      "text": "Що таке критична секція в Windows?"
    },
    {
      "topic": "Паралельне програмування",
      "text": "Які умови необхідні для виникнення deadlock?"
    },
    {
      "topic": "Паралельне програмування",
      "text": "Які способи уникнення deadlock ви знаєте? Що таке livelock?"
    },
    {
      "topic": "Паралельне програмування",
      "text": "Що таке non-blocking програмування? Що означають поняття wait-free, lock-free, obstruction-free?"
    },
    {
      "topic": "Паралельне програмування",
      "text": "Які етапи розробки паралельних задач містить методологія PCAM?"
    },
    {
      "topic": "Паралельне програмування",
      "text": "Опишіть суть етапів PCAM. У чому різниця між domain decomposition та functional decomposition? Наведіть приклад використання PCAM."
    },
    {
      "topic": "Паралельне програмування",
      "text": "Які способи зменшення об'єму комунікації в рамках методології PCAM ви знаєте?"
    },
    {
      "topic": "Паралельне програмування",
      "text": "Що таке бар’єр пам’яті? Як реалізувати memory barrier у C++?"
    },
    {
      "topic": "Паралельне програмування",
      "text": "Що таке співпрограма (coroutine)?"
    },
    {
      "topic": "Паралельне програмування",
      "text": "Що таке compare-and-swap (CAS)? Для чого потрібен? Що таке test-and-set? Яку роль відіграє інструкція XCHG у x86?"
    },
    {
      "topic": "Паралельне програмування",
      "text": "Поясніть ідею конструкції LL/SC."
    },
    {
      "topic": "Паралельне програмування",
      "text": "Що таке Executor? Які є їх різновиди? Що таке thread_pool?"
    },
    {
      "topic": "Паралельне програмування",
      "text": "Що таке future та promise у C++? Для чого використовуються? Що таке continuations? Як застосовувати when_all(), when_any(), reduce()?"
    },
    {
      "topic": "Паралельне програмування",
      "text": "Які паралельні алгоритми є в стандартній бібліотеці C++17? Які політики виконання вони підтримують? У чому суть підходу MapReduce?"
    },
    {
      "topic": "Кеш пам'ять",
      "text": "Що таке кеш пам’яті, на яких принципах базується його використання?"
    },
    {
      "topic": "Кеш пам'ять",
      "text": "Що таке cache hit та cache miss? Які міри ефективності кешів пам’яті ви знаєте?"
    },
    {
      "topic": "Кеш пам'ять",
      "text": "Чим відрізняються кеші пам'яті першого, другого рівнів тощо? В чому різниця між L1i та L1d, і чому існує потреба в такому розділенні?"
    },
    {
      "topic": "Кеш пам'ять",
      "text": "Що таке рядок кешу (cacheline), з яких частин він складається? Що таке тег (tag) рядка кешу, які прапорці необхідні в ньому? Який типовий розмір рядка кешу сучасних процесорів x86?"
    },
    {
      "topic": "Кеш пам'ять",
      "text": "Що таке повно-асоціативний кеш (fully associative cache), кеш прямого відображення (direct mapped cache), N-канальний асоціативний кеш (set-associative cache)? Порівняйте їх переваги та недоліки."
    },
    {
      "topic": "Кеш пам'ять",
      "text": "Що таке буфер запису (write buffer) в мікроархітектурі? Що таке victim buffer?"
    },
    {
      "topic": "Кеш пам'ять",
      "text": "В чому різниця між інклюзивним та ексклюзивним кешами?"
    },
    {
      "topic": "Кеш пам'ять",
      "text": "Які існують політики запису кешу пам’яті?"
    },
    {
      "topic": "Кеш пам'ять",
      "text": "Які види промахів кешу існують? Як боротися з compulsory, capacity та conflict misses? Як програмно зробити так, щоб певні дані не кешувались?"
    },
    {
      "topic": "Кеш пам'ять",
      "text": "Для чого потрібен prefetcher в CPU? Як він організований?"
    },
    {
      "topic": "Кеш пам'ять",
      "text": "Які способи визначення адрес для попередньої вибірки (prefetching) використовуються?"
    },
    {
      "topic": "Кеш пам'ять",
      "text": "Що таке stream buffer?"
    },
    {
      "topic": "Кеш пам'ять",
      "text": "Як програмно можна здійснювати попередню вибірку (prefetching), якщо апаратний prefetcher відсутній або неефективний? Які критерії ефективності попередньої вибірки використовуються?"
    },
    {
      "topic": "Кеш пам'ять",
      "text": "В чому суть багів Meltdown та Spectre?"
    },
    {
      "topic": "Кеш пам'ять",
      "text": "Опишіть ієрархію пам’яті сучасних процесорів. Чому вона така?"
    },
    {
      "topic": "Кеш пам'ять",
      "text": "Які політики запису кешу пам’яті ви знаєте? Проєктуючи новий процесор, яку з політик — write-back чи write-through — ви виберете і чому?"
    },
    {
      "topic": "Кеш пам'ять",
      "text": "Команда, що виконується спекулятивно, виконує запис. Чи обов’язково мусить зупинитися конвеєр? Який механізм дозволяє цього уникнути?"
    }
  ]
}
